{
  "company": {
    "baseMenu": {
      "home": "Dom콢",
      "listings": "Inzer치ty",
      "services": "Slu쬭y",
      "account": "칔캜et",
      "menu": "Menu"
    },
    "newListing": {
      "steps": {
        "companyData": {
          "title": "Registrace firmy",
          "leftPart": {
            "title": "칔daje o spole캜nosti",
            "inputs": {
              "companyName": {
                "label": "N치zev spole캜nosti",
                "placeholder": "ROO s.r.o"
              },
              "ico": {
                "label": "I캛O",
                "placeholder": "123456789"
              },
              "dic": {
                "label": "DI캛",
                "placeholder": "CZ123456789"
              },
              "street": {
                "label": "Ulice",
                "placeholder": "Ulice 123"
              },
              "city": {
                "label": "M캩sto",
                "placeholder": "Praha"
              },
              "cityCode": {
                "label": "PS캛",
                "placeholder": "12345"
              },
              "country": {
                "label": "Zem캩",
                "placeholder": "Vyberte zemi"
              }
            }
          },
          "rightPart": {
            "title": "Hlavn칤 kontaktn칤 osoba",
            "inputs": {
              "firstName": {
                "label": "Jm칠no",
                "placeholder": "Jan"
              },
              "lastName": {
                "label": "P콏칤jmen칤",
                "placeholder": "Nov치k"
              },
              "phone": {
                "label": "Telefon",
                "placeholder": "123 456 789"
              },
              "email": {
                "label": "E-mail",
                "placeholder": "jan.novak@example.com"
              }
            }
          },
          "button": "Pokra캜ovat",
          "legal": "Souhlas칤m s obchodn칤mi podm칤nkami a z치sadami ochrany osobn칤ch 칰daj콢.",
          "marketing": "Chci dost치vat marketingov칠 e-maily o novink치ch a nab칤dk치ch.",
          "success": {
            "title": "Gratulujeme!",
            "message": "U jsi o krok bl칤 k 칰sp캩코n칠mu profilu! Poj캞me te캞 nastavit tv콢j prvn칤 inzer치t.",
            "button": "Pokra캜ovat"
          }
        },
        "listingType": {
          "title": "Jak칠 slu쬭y poskytuje코?",
          "subtitle": "Vyber jednu nebo v칤ce kategori칤 kliknut칤m na ikonu",
          "cards": {
            "gastro": {
              "title": "Gastro",
              "description": "D캩l치코 catering, m치코 foodtruck nebo bar na eventy."
            },
            "place": {
              "title": "M칤sto",
              "description": "M치코 prostory, kde po콏치d치코 akce."
            },
            "entertainment": {
              "title": "Z치bava",
              "description": "Jsi DJ, kapela, moder치tor, kouzeln칤k, tane캜nice nebo jakkoliv bav칤코 hosty"
            }
          },
          "button": "Pokra캜ovat",
          "buttonBack": "Zp캩t",
          "pickOne": {
            "title": "Jakou slu쬭u chce코 nastavit jako prvn칤?",
            "subheading": "Druhou slu쬭u bude코 m칤t mo쬹ost nastavit pozd캩ji.",
            "button": "Pokra캜ovat",
            "buttonBack": "Zp캩t"
          }
        },
        "listingName": {
          "gastro": {
            "title": "N치zev slu쬭y",
            "subtitle": "Jak se m치 tvoje slu쬭a jmenovat?",
            "input": {
              "label": "N치zev slu쬭y",
              "placeholder": "N치zev m칠 slu쬭y"
            },
            "button": "Pokra캜ovat",
            "buttonBack": "Zp캩t"
          },
          "place": {
            "title": "N치zev m칤sta",
            "subtitle": "Jak se m치 tvoje m칤sto jmenovat?",
            "input": {
              "label": "N치zev m칤sta",
              "placeholder": "N치zev m칠ho m칤sta"
            },
            "button": "Pokra캜ovat",
            "buttonBack": "Zp캩t"
          },
          "entertainment": {
            "title": "N치zev slu쬭y",
            "subtitle": "Jak se m치 tvoje slu쬭a jmenovat?",
            "input": {
              "label": "N치zev slu쬭y",
              "placeholder": "N치zev m칠 slu쬭y"
            },
            "button": "Pokra캜ovat",
            "buttonBack": "Zp캩t"
          }
        },
        "specification": {
          "place": {
            "heading": "Co za m칤sto nab칤z칤코?",
            "subheading": "Te캞 pot콏ebujeme p콏esn캩 specifikovat m칤sto, kter칠 nab칤z칤코. Typ콢 m콢쬰 b칳t klidn캩 v칤c, tak쬰 to po콏치dn캩 popi코.",
            "input": {
              "label": "Typ m칤sta",
              "placeholder": "P콏idej dal코칤"
            },
            "buttonContinue": "Pokra캜ovat",
            "buttonBack": "Zp캩t"
          },
          "gastro": {
            "heading": "Co za slu쬭u nab칤z칤코?",
            "subheading": "Te캞 pot콏ebujeme p콏esn캩 specifikovat slu쬭u, kterou nab칤z칤코. Typ콢 m콢쬰 b칳t klidn캩 v칤c, tak쬰 to po콏치dn캩 popi코.",
            "input": {
              "label": "Typ slu쬭y",
              "placeholder": "P콏idej dal코칤"
            },
            "buttonContinue": "Pokra캜ovat",
            "buttonBack": "Zp캩t"
          },
          "entertainment": {
            "heading": "Co za slu쬭u nab칤z칤코?",
            "subheading": "Te캞 pot콏ebujeme p콏esn캩 specifikovat slu쬭u, kterou nab칤z칤코. Typ콢 m콢쬰 b칳t klidn캩 v칤c, tak쬰 to po콏치dn캩 popi코.",
            "input": {
              "label": "Typ slu쬭y",
              "placeholder": "P콏idej dal코칤"
            },
            "buttonContinue": "Pokra캜ovat",
            "buttonBack": "Zp캩t"
          }
        },
        "location": {
          "place": {
            "stepOne": {
              "title": "Kde se tvoje m칤sto nach치z칤?",
              "subtitle": "Zadej p콏esnou adresu. Pokud je adresa stejn치 jako s칤dlo tv칠 firmy, zaklikni pole Adresa je stejn치 jako faktura캜n칤 칰daje"
            },
            "stepTwo": {
              "title": "Vyberte oblasti, kde poskytujete slu쬭y",
              "subtitle": "M콢쬰te vybrat v칤ce kraj콢, okres콢 a m캩st najednou"
            },
            "inputs": {
              "sameAsInvoicing": "Adresa je stejn치 jako faktura캜n칤 칰daje",
              "serviceArea": "Poskytuji slu쬭u ve v칤ce lokalit치ch",
              "street": {
                "label": "Ulice",
                "placeholder": "Ulice 123"
              },
              "city": {
                "label": "M캩sto",
                "placeholder": "Praha"
              },
              "cityCode": {
                "label": "PS캛",
                "placeholder": "100 00"
              },
              "country": {
                "label": "Zem캩",
                "placeholder": "Vyberte zemi"
              }
            },
            "buttonContinue": "Pokra캜ovat",
            "buttonBack": "Zp캩t"
          },
          "gastro": {
            "stepOne": {
              "title": "Kde se tvoje slu쬭a nach치z칤?",
              "subtitle": "Zadej p콏esnou adresu. Pokud je adresa stejn치 jako s칤dlo tv칠 firmy, zaklikni pole Adresa je stejn치 jako faktura캜n칤 칰daje"
            },
            "stepTwo": {
              "title": "Vyberte oblasti, kde poskytujete slu쬭y",
              "subtitle": "M콢쬰te vybrat v칤ce kraj콢, okres콢 a m캩st najednou",
              "inputs": {
                "country": {
                  "label": "Zem캩",
                  "placeholder": "Vyberte zem캩"
                },
                "region": {
                  "label": "Kraje",
                  "placeholder": "Vyberte kraje"
                },
                "district": {
                  "label": "Okresy",
                  "placeholder": "Vyberte okresy"
                },
                "city": {
                  "label": "M캩sta",
                  "placeholder": "Vyberte m캩sta"
                }
              }
            },
            "inputs": {
              "sameAsInvoicing": "Adresa je stejn치 jako faktura캜n칤 칰daje",
              "serviceArea": "Poskytuji slu쬭u ve v칤ce lokalit치ch",
              "street": {
                "label": "Ulice",
                "placeholder": "Ulice 123"
              },
              "city": {
                "label": "M캩sto",
                "placeholder": "Praha"
              },
              "cityCode": {
                "label": "PS캛",
                "placeholder": "100 00"
              },
              "country": {
                "label": "Zem캩",
                "placeholder": "Vyberte zemi"
              }
            },
            "buttonContinue": "Pokra캜ovat",
            "buttonBack": "Zp캩t"
          },
          "entertainment": {
            "stepOne": {
              "title": "Kde se tvoje slu쬭a nach치z칤?",
              "subtitle": "Zadej p콏esnou adresu. Pokud je adresa stejn치 jako s칤dlo tv칠 firmy, zaklikni pole Adresa je stejn치 jako faktura캜n칤 칰daje"
            },
            "stepTwo": {
              "title": "Vyberte oblasti, kde poskytujete slu쬭y",
              "subtitle": "M콢쬰te vybrat v칤ce kraj콢, okres콢 a m캩st najednou",
              "inputs": {
                "country": {
                  "label": "Zem캩",
                  "placeholder": "Vyberte zem캩"
                },
                "region": {
                  "label": "Kraje",
                  "placeholder": "Vyberte kraje"
                },
                "district": {
                  "label": "Okresy",
                  "placeholder": "Vyberte okresy"
                },
                "city": {
                  "label": "M캩sta",
                  "placeholder": "Vyberte m캩sta"
                }
              }
            },
            "inputs": {
              "sameAsInvoicing": "Adresa je stejn치 jako faktura캜n칤 칰daje",
              "serviceArea": "Poskytuji slu쬭u ve v칤ce lokalit치ch",
              "street": {
                "label": "Ulice",
                "placeholder": "Ulice 123"
              },
              "city": {
                "label": "M캩sto",
                "placeholder": "Praha"
              },
              "cityCode": {
                "label": "PS캛",
                "placeholder": "100 00"
              },
              "country": {
                "label": "Zem캩",
                "placeholder": "Vyberte zemi"
              }
            },
            "buttonContinue": "Pokra캜ovat",
            "buttonBack": "Zp캩t"
          }
        },
        "summary": {
          "title": "Par치da! Z치klad je hotov칳!",
          "congratulations": "칔vodn칤 kostra tv칠ho inzer치tu je p콏ipraven치. Te캞 u jen doplnit detaily a m콢쬰코 za캜칤t sb칤rat popt치vky! 游꿀 Dal코칤 kroky najde코 v administraci, do kter칠 p콏ejde코 tla캜칤tkem n칤쬰.",
          "fill_more": "Na za캜치tku jsi n치m 콏ekl, 쬰 m치코 pod stejnou firmou v칤ce slu쬰b. Pokud te캞 chce코 p콏idat dal코칤, m콢쬰코 tak u캜init tla캜칤tky n칤쬰.",
          "buttons": {
            "start_gastro": "P콏idat gastro",
            "start_place": "P콏idat m칤sto",
            "start_entertainment": "P콏idat z치bavu",
            "to_admin": "P콏ej칤t do administrace",
            "back": "Zp캩t"
          }
        }
      }
    }
  }
}
